Workbook
Name Slicer_CATEGORY: #N/A
Name Slicer_CUSTOMER_TYPE: #N/A
Name Slicer_CITY: #N/A
Name Slicer_DATE: #N/A

Sheet KING TON SALES__ RAW DATA
A1: PRODUCT ID | B1: PRODUCT NAME | C1: DATE | D1: CATEGORY | E1: CUSTOMER TYPE | F1: CITY | G1: COST PRICE | H1: STOCK | I1: SELLING PRICE | J1: QUANTITY SOLD | K1: TOTAL COST | L1: REVENUE | M1: PAYMENT METHOD | O1: DATE A | P1: DATE B
A2: P001 | B2: 3 TO 3 AV (1.5m) WIRE | C2: =RANDBETWEEN(DATE(2026,1,1),DATE(2026,4,30)) -> 46070 | D2: WIRE | E2: MEMEBER | F2: WARRI | G2: 600 | H2: 50 | I2: 1500 | J2: =RANDBETWEEN(15,20) -> 18 | K2: =G2*J2 -> 10800 | L2: =I2*J2 -> 27000 | M2: POS | O2: =DATE(2026,1,1) -> 46023 | P2: =DATE(2026,9,12) -> 46277
A3: P002 | B3: 2 TO 2 AV (1.5m) WIRE | C3: =RANDBETWEEN(DATE(2026,1,1),DATE(2026,4,30)) -> 46101 | D3: WIRE | E3: NORMAL | F3: WARRI | G3: 500 | H3: 63 | I3: 1000 | J3: =RANDBETWEEN(15,20) -> 20 | K3: =G3*J3 -> 10000 | L3: =I3*J3 -> 20000 | M3: CASH
A4: P003 | B4: AUX TO 2 AV ( 1.5m) WIRE | C4: =RANDBETWEEN(DATE(2026,1,1),DATE(2026,4,30)) -> 46109 | D4: WIRE | E4: NORMAL | F4: WARRI | G4: 500 | H4: 67 | I4: 1500 | J4: =RANDBETWEEN(15,20) -> 17 | K4: =G4*J4 -> 8500 | L4: =I4*J4 -> 25500 | M4: POS
A5: P004 | B5: 1 TO 1 AUX (1.5m) WIRE | C5: =RANDBETWEEN(DATE(2026,1,1),DATE(2026,4,30)) -> 46115 | D5: WIRE | E5: MEMEBER | F5: WARRI | G5: 500 | H5: 59 | I5: 1000 | J5: =RANDBETWEEN(15,20) -> 18 | K5: =G5*J5 -> 9000 | L5: =I5*J5 -> 18000 | M5: TRANSFER
A6: P005 | B6: AUX TO JACK (1.5m) WIRE | C6: =RANDBETWEEN(DATE(2026,1,1),DATE(2026,4,30)) -> 46133 | D6: WIRE | E6: NORMAL | F6: SAPELE | G6: 600 | H6: 57 | I6: 1000 | J6: =RANDBETWEEN(15,20) -> 15 | K6: =G6*J6 -> 9000 | L6: =I6*J6 -> 15000 | M6: TRANSFER
A7: P006 | B7: JACK TO JACK (1.5m) WIRE | C7: =RANDBETWEEN(DATE(2026,1,1),DATE(2026,4,30)) -> 46041 | D7: WIRE | E7: MEMEBER | F7: UGHELLI | G7: 600 | H7: 67 | I7: 1500 | J7: =RANDBETWEEN(15,20) -> 16 | K7: =G7*J7 -> 9600 | L7: =I7*J7 -> 24000 | M7: POS
A8: P007 | B8: JACK TO JACK (5m) WIRE | C8: =RANDBETWEEN(DATE(2026,1,1),DATE(2026,4,30)) -> 46092 | D8: WIRE | E8: NORMAL | F8: WARRI | G8: 800 | H8: 46 | I8: 2500 | J8: =RANDBETWEEN(15,20) -> 15 | K8: =G8*J8 -> 12000 | L8: =I8*J8 -> 37500 | M8: POS
A9: P008 | B9: 3 TO 3 AV (5m) WIRE | C9: =RANDBETWEEN(DATE(2026,1,1),DATE(2026,4,30)) -> 46080 | D9: WIRE | E9: NORMAL | F9: UGHELLI | G9: 1200 | H9: 45 | I9: 2500 | J9: =RANDBETWEEN(15,20) -> 20 | K9: =G9*J9 -> 24000 | L9: =I9*J9 -> 50000 | M9: POS
A10: P009 | B10: 3 TO 3 AV (10m) WIRE | C10: =RANDBETWEEN(DATE(2026,1,1),DATE(2026,4,30)) -> 46138 | D10: WIRE | E10: MEMEBER | F10: AGBARO | G10: 1500 | H10: 36 | I10: 3500 | J10: =RANDBETWEEN(15,20) -> 18 | K10: =G10*J10 -> 27000 | L10: =I10*J10 -> 63000 | M10: POS
A11: P010 | B11: 3 TO 3 AV (15m) WIRE | C11: =RANDBETWEEN(DATE(2026,1,1),DATE(2026,4,30)) -> 46051 | D11: WIRE | E11: NORMAL | F11: AGBARO | G11: 2500 | H11: 32 | I11: 5000 | J11: =RANDBETWEEN(15,20) -> 19 | K11: =G11*J11 -> 47500 | L11: =I11*J11 -> 95000 | M11: POS
A12: P011 | B12: HDMI (1.5m) WIRE | C12: =RANDBETWEEN(DATE(2026,1,1),DATE(2026,4,30)) -> 46069 | D12: WIRE | E12: MEMEBER | F12: WARRI | G12: 600 | H12: 30 | I12: 1000 | J12: =RANDBETWEEN(15,20) -> 18 | K12: =G12*J12 -> 10800 | L12: =I12*J12 -> 18000 | M12: CASH
A13: P012 | B13: HDMI (3m) WIRE | C13: =RANDBETWEEN(DATE(2026,1,1),DATE(2026,4,30)) -> 46071 | D13: WIRE | E13: NORMAL | F13: SAPELE | G13: 600 | H13: 35 | I13: 1500 | J13: =RANDBETWEEN(15,20) -> 20 | K13: =G13*J13 -> 12000 | L13: =I13*J13 -> 30000 | M13: CASH
A14: P013 | B14: HDMI (5m) WIRE | C14: =RANDBETWEEN(DATE(2026,1,1),DATE(2026,4,30)) -> 46094 | D14: WIRE | E14: NORMAL | F14: OGHULA | G14: 1200 | H14: 39 | I14: 2500 | J14: =RANDBETWEEN(15,20) -> 17 | K14: =G14*J14 -> 20400 | L14: =I14*J14 -> 42500 | M14: CASH
... A271: P270 | B271: AHUJA SUH-10 | C271: =RANDBETWEEN(DATE(2026,1,1),DATE(2026,4,30)) -> 46141 | D271: SPEAKER | E271: NORMAL | F271: WARRI | G271: 15000 | H271: 67 | I271: 20000 | J271: =RANDBETWEEN(15,20) -> 16 | K271: =G271*J271 -> 240000 | L271: =I271*J271 -> 320000 | M271: POS

Sheet SALES ANALYSIS 
A1: INVOICE No. | B1: DATE | C1: CITY | D1: CUSTOMER TYPE | E1: PRODUCT ID | F1: PRODUCT NAME | G1: CATEGORY | H1: COST PRICE | I1: QUANTITY SOLD | J1: SELLING PRICE | K1: COGS | L1: REVENUE | M1: TOTAL PROFIT | N1: PAYMENT METHOD
A2: 6663 | B2: 46210 | C2: SAPELE | D2: NORMAL | E2: P042 | F2: =_xlfn.XLOOKUP(E2,'KING TON SALES__ RAW DATA'!$A$2:$A$271,'KING TON SALES__ RAW DATA'!$B$2:$B$271) -> OPTICAL CABLE (1.5m) | G2: =_xlfn.XLOOKUP(E2,'KING TON SALES__ RAW DATA'!$A$2:$A$271,'KING TON SALES__ RAW DATA'!$D$2:$D$271) -> WIRE | H2: =_xlfn.XLOOKUP(E2,'KING TON SALES__ RAW DATA'!$A$2:$A$271,'KING TON SALES__ RAW DATA'!$G$2:$G$271) -> 1500 | I2: 17 | J2: =_xlfn.XLOOKUP(E2,'KING TON SALES__ RAW DATA'!$A$2:$A$271,'KING TON SALES__ RAW DATA'!$I$2:$I$271) -> 3500 | K2: =H2*I2 -> 25500 | L2: =J2*I2 -> 59500 | M2: =L2-K2 -> 34000 | N2: =_xlfn.XLOOKUP(E2,'KING TON SALES__ RAW DATA'!$A$2:$A$271,'KING TON SALES__ RAW DATA'!$M$2:$M$271) -> CASH
A3: 6664 | B3: 46237 | C3: WARRI | D3: MEMEBER | E3: P001 | F3: =_xlfn.XLOOKUP(E3,'KING TON SALES__ RAW DATA'!$A$2:$A$271,'KING TON SALES__ RAW DATA'!$B$2:$B$271) -> 3 TO 3 AV (1.5m) WIRE | G3: =_xlfn.XLOOKUP(E3,'KING TON SALES__ RAW DATA'!$A$2:$A$271,'KING TON SALES__ RAW DATA'!$D$2:$D$271) -> WIRE | H3: =_xlfn.XLOOKUP(E3,'KING TON SALES__ RAW DATA'!$A$2:$A$271,'KING TON SALES__ RAW DATA'!$G$2:$G$271) -> 600 | I3: 17 | J3: =_xlfn.XLOOKUP(E3,'KING TON SALES__ RAW DATA'!$A$2:$A$271,'KING TON SALES__ RAW DATA'!$I$2:$I$271) -> 1500 | K3: =H3*I3 -> 10200 | L3: =J3*I3 -> 25500 | M3: =L3-K3 -> 15300 | N3: =_xlfn.XLOOKUP(E3,'KING TON SALES__ RAW DATA'!$A$2:$A$271,'KING TON SALES__ RAW DATA'!$M$2:$M$271) -> POS
A4: 6665 | B4: 46255 | C4: WARRI | D4: NORMAL | E4: P047 | F4: =_xlfn.XLOOKUP(E4,'KING TON SALES__ RAW DATA'!$A$2:$A$271,'KING TON SALES__ RAW DATA'!$B$2:$B$271) -> 13 AMPS DOUBLE SOCKET BENJOR | G4: =_xlfn.XLOOKUP(E4,'KING TON SALES__ RAW DATA'!$A$2:$A$271,'KING TON SALES__ RAW DATA'!$D$2:$D$271) -> ELECTRICAL | H4: =_xlfn.XLOOKUP(E4,'KING TON SALES__ RAW DATA'!$A$2:$A$271,'KING TON SALES__ RAW DATA'!$G$2:$G$271) -> 2500 | I4: 17 | J4: =_xlfn.XLOOKUP(E4,'KING TON SALES__ RAW DATA'!$A$2:$A$271,'KING TON SALES__ RAW DATA'!$I$2:$I$271) -> 5000 | K4: =H4*I4 -> 42500 | L4: =J4*I4 -> 85000 | M4: =L4-K4 -> 42500 | N4: =_xlfn.XLOOKUP(E4,'KING TON SALES__ RAW DATA'!$A$2:$A$271,'KING TON SALES__ RAW DATA'!$M$2:$M$271) -> POS
A5: 6666 | B5: 46209 | C5: WARRI | D5: NORMAL | E5: P062 | F5: =_xlfn.XLOOKUP(E5,'KING TON SALES__ RAW DATA'!$A$2:$A$271,'KING TON SALES__ RAW DATA'!$B$2:$B$271) -> 777 9v BATTERY | G5: =_xlfn.XLOOKUP(E5,'KING TON SALES__ RAW DATA'!$A$2:$A$271,'KING TON SALES__ RAW DATA'!$D$2:$D$271) -> BATTERY | H5: =_xlfn.XLOOKUP(E5,'KING TON SALES__ RAW DATA'!$A$2:$A$271,'KING TON SALES__ RAW DATA'!$G$2:$G$271) -> 250 | I5: 20 | J5: =_xlfn.XLOOKUP(E5,'KING TON SALES__ RAW DATA'!$A$2:$A$271,'KING TON SALES__ RAW DATA'!$I$2:$I$271) -> 500 | K5: =H5*I5 -> 5000 | L5: =J5*I5 -> 10000 | M5: =L5-K5 -> 5000 | N5: =_xlfn.XLOOKUP(E5,'KING TON SALES__ RAW DATA'!$A$2:$A$271,'KING TON SALES__ RAW DATA'!$M$2:$M$271) -> TRANSFER
A6: 6667 | B6: 46226 | C6: AGBARO | D6: MEMEBER | E6: P039 | F6: =_xlfn.XLOOKUP(E6,'KING TON SALES__ RAW DATA'!$A$2:$A$271,'KING TON SALES__ RAW DATA'!$B$2:$B$271) -> USB TO FEMALE USB (1.5m) CORD | G6: =_xlfn.XLOOKUP(E6,'KING TON SALES__ RAW DATA'!$A$2:$A$271,'KING TON SALES__ RAW DATA'!$D$2:$D$271) -> WIRE | H6: =_xlfn.XLOOKUP(E6,'KING TON SALES__ RAW DATA'!$A$2:$A$271,'KING TON SALES__ RAW DATA'!$G$2:$G$271) -> 2500 | I6: 21 | J6: =_xlfn.XLOOKUP(E6,'KING TON SALES__ RAW DATA'!$A$2:$A$271,'KING TON SALES__ RAW DATA'!$I$2:$I$271) -> 5000 | K6: =H6*I6 -> 52500 | L6: =J6*I6 -> 105000 | M6: =L6-K6 -> 52500 | N6: =_xlfn.XLOOKUP(E6,'KING TON SALES__ RAW DATA'!$A$2:$A$271,'KING TON SALES__ RAW DATA'!$M$2:$M$271) -> TRANSFER
A7: 6668 | B7: 46236 | C7: AGBARO | D7: MEMEBER | E7: P054 | F7: =_xlfn.XLOOKUP(E7,'KING TON SALES__ RAW DATA'!$A$2:$A$271,'KING TON SALES__ RAW DATA'!$B$2:$B$271) -> BENJOR MULTI WITH SWITCH | G7: =_xlfn.XLOOKUP(E7,'KING TON SALES__ RAW DATA'!$A$2:$A$271,'KING TON SALES__ RAW DATA'!$D$2:$D$271) -> ELECTRICAL | H7: =_xlfn.XLOOKUP(E7,'KING TON SALES__ RAW DATA'!$A$2:$A$271,'KING TON SALES__ RAW DATA'!$G$2:$G$271) -> 1000 | I7: 21 | J7: =_xlfn.XLOOKUP(E7,'KING TON SALES__ RAW DATA'!$A$2:$A$271,'KING TON SALES__ RAW DATA'!$I$2:$I$271) -> 3000 | K7: =H7*I7 -> 21000 | L7: =J7*I7 -> 63000 | M7: =L7-K7 -> 42000 | N7: =_xlfn.XLOOKUP(E7,'KING TON SALES__ RAW DATA'!$A$2:$A$271,'KING TON SALES__ RAW DATA'!$M$2:$M$271) -> POS
A8: 6669 | B8: 46230 | C8: WARRI | D8: NORMAL | E8: P030 | F8: =_xlfn.XLOOKUP(E8,'KING TON SALES__ RAW DATA'!$A$2:$A$271,'KING TON SALES__ RAW DATA'!$B$2:$B$271) -> DC TO DC MALE (3m) WIRE | G8: =_xlfn.XLOOKUP(E8,'KING TON SALES__ RAW DATA'!$A$2:$A$271,'KING TON SALES__ RAW DATA'!$D$2:$D$271) -> WIRE | H8: =_xlfn.XLOOKUP(E8,'KING TON SALES__ RAW DATA'!$A$2:$A$271,'KING TON SALES__ RAW DATA'!$G$2:$G$271) -> 500 | I8: 20 | J8: =_xlfn.XLOOKUP(E8,'KING TON SALES__ RAW DATA'!$A$2:$A$271,'KING TON SALES__ RAW DATA'!$I$2:$I$271) -> 1000 | K8: =H8*I8 -> 10000 | L8: =J8*I8 -> 20000 | M8: =L8-K8 -> 10000 | N8: =_xlfn.XLOOKUP(E8,'KING TON SALES__ RAW DATA'!$A$2:$A$271,'KING TON SALES__ RAW DATA'!$M$2:$M$271) -> POS
A9: 6670 | B9: 46240 | C9: WARRI | D9: NORMAL | E9: P063 | F9: =_xlfn.XLOOKUP(E9,'KING TON SALES__ RAW DATA'!$A$2:$A$271,'KING TON SALES__ RAW DATA'!$B$2:$B$271) -> HI/WATT 9v BATTERY | G9: =_xlfn.XLOOKUP(E9,'KING TON SALES__ RAW DATA'!$A$2:$A$271,'KING TON SALES__ RAW DATA'!$D$2:$D$271) -> BATTERY | H9: =_xlfn.XLOOKUP(E9,'KING TON SALES__ RAW DATA'!$A$2:$A$271,'KING TON SALES__ RAW DATA'!$G$2:$G$271) -> 250 | I9: 21 | J9: =_xlfn.XLOOKUP(E9,'KING TON SALES__ RAW DATA'!$A$2:$A$271,'KING TON SALES__ RAW DATA'!$I$2:$I$271) -> 500 | K9: =H9*I9 -> 5250 | L9: =J9*I9 -> 10500 | M9: =L9-K9 -> 5250 | N9: =_xlfn.XLOOKUP(E9,'KING TON SALES__ RAW DATA'!$A$2:$A$271,'KING TON SALES__ RAW DATA'!$M$2:$M$271) -> POS
A10: 6671 | B10: 46260 | C10: AGBARO | D10: MEMEBER | E10: P054 | F10: =_xlfn.XLOOKUP(E10,'KING TON SALES__ RAW DATA'!$A$2:$A$271,'KING TON SALES__ RAW DATA'!$B$2:$B$271) -> BENJOR MULTI WITH SWITCH | G10: =_xlfn.XLOOKUP(E10,'KING TON SALES__ RAW DATA'!$A$2:$A$271,'KING TON SALES__ RAW DATA'!$D$2:$D$271) -> ELECTRICAL | H10: =_xlfn.XLOOKUP(E10,'KING TON SALES__ RAW DATA'!$A$2:$A$271,'KING TON SALES__ RAW DATA'!$G$2:$G$271) -> 1000 | I10: 21 | J10: =_xlfn.XLOOKUP(E10,'KING TON SALES__ RAW DATA'!$A$2:$A$271,'KING TON SALES__ RAW DATA'!$I$2:$I$271) -> 3000 | K10: =H10*I10 -> 21000 | L10: =J10*I10 -> 63000 | M10: =L10-K10 -> 42000 | N10: =_xlfn.XLOOKUP(E10,'KING TON SALES__ RAW DATA'!$A$2:$A$271,'KING TON SALES__ RAW DATA'!$M$2:$M$271) -> POS
A11: 6672 | B11: 46235 | C11: WARRI | D11: NORMAL | E11: P022 | F11: =_xlfn.XLOOKUP(E11,'KING TON SALES__ RAW DATA'!$A$2:$A$271,'KING TON SALES__ RAW DATA'!$B$2:$B$271) -> 4K HDMI (50m) WIRE | G11: =_xlfn.XLOOKUP(E11,'KING TON SALES__ RAW DATA'!$A$2:$A$271,'KING TON SALES__ RAW DATA'!$D$2:$D$271) -> WIRE | H11: =_xlfn.XLOOKUP(E11,'KING TON SALES__ RAW DATA'!$A$2:$A$271,'KING TON SALES__ RAW DATA'!$G$2:$G$271) -> 30000 | I11: 18 | J11: =_xlfn.XLOOKUP(E11,'KING TON SALES__ RAW DATA'!$A$2:$A$271,'KING TON SALES__ RAW DATA'!$I$2:$I$271) -> 45000 | K11: =H11*I11 -> 540000 | L11: =J11*I11 -> 810000 | M11: =L11-K11 -> 270000 | N11: =_xlfn.XLOOKUP(E11,'KING TON SALES__ RAW DATA'!$A$2:$A$271,'KING TON SALES__ RAW DATA'!$M$2:$M$271) -> TRANSFER
A12: 6673 | B12: 46242 | C12: WARRI | D12: NORMAL | E12: P017 | F12: =_xlfn.XLOOKUP(E12,'KING TON SALES__ RAW DATA'!$A$2:$A$271,'KING TON SALES__ RAW DATA'!$B$2:$B$271) -> HDMI (30m) WIRE | G12: =_xlfn.XLOOKUP(E12,'KING TON SALES__ RAW DATA'!$A$2:$A$271,'KING TON SALES__ RAW DATA'!$D$2:$D$271) -> WIRE | H12: =_xlfn.XLOOKUP(E12,'KING TON SALES__ RAW DATA'!$A$2:$A$271,'KING TON SALES__ RAW DATA'!$G$2:$G$271) -> 10000 | I12: 24 | J12: =_xlfn.XLOOKUP(E12,'KING TON SALES__ RAW DATA'!$A$2:$A$271,'KING TON SALES__ RAW DATA'!$I$2:$I$271) -> 15000 | K12: =H12*I12 -> 240000 | L12: =J12*I12 -> 360000 | M12: =L12-K12 -> 120000 | N12: =_xlfn.XLOOKUP(E12,'KING TON SALES__ RAW DATA'!$A$2:$A$271,'KING TON SALES__ RAW DATA'!$M$2:$M$271) -> TRANSFER
A13: 6674 | B13: 46245 | C13: SAPELE | D13: NORMAL | E13: P057 | F13: =_xlfn.XLOOKUP(E13,'KING TON SALES__ RAW DATA'!$A$2:$A$271,'KING TON SALES__ RAW DATA'!$B$2:$B$271) -> BENJOR EXTENTION 3 MOUTH | G13: =_xlfn.XLOOKUP(E13,'KING TON SALES__ RAW DATA'!$A$2:$A$271,'KING TON SALES__ RAW DATA'!$D$2:$D$271) -> ELECTRICAL | H13: =_xlfn.XLOOKUP(E13,'KING TON SALES__ RAW DATA'!$A$2:$A$271,'KING TON SALES__ RAW DATA'!$G$2:$G$271) -> 2000 | I13: 25 | J13: =_xlfn.XLOOKUP(E13,'KING TON SALES__ RAW DATA'!$A$2:$A$271,'KING TON SALES__ RAW DATA'!$I$2:$I$271) -> 7000 | K13: =H13*I13 -> 50000 | L13: =J13*I13 -> 175000 | M13: =L13-K13 -> 125000 | N13: =_xlfn.XLOOKUP(E13,'KING TON SALES__ RAW DATA'!$A$2:$A$271,'KING TON SALES__ RAW DATA'!$M$2:$M$271) -> CASH
... A301: 6962 | B301: 46155 | C301: SAPELE | D301: NORMAL | E301: P087 | F301: =_xlfn.XLOOKUP(E301,'KING TON SALES__ RAW DATA'!$A$2:$A$271,'KING TON SALES__ RAW DATA'!$B$2:$B$271) -> SONIK 12V 7AH | G301: =_xlfn.XLOOKUP(E301,'KING TON SALES__ RAW DATA'!$A$2:$A$271,'KING TON SALES__ RAW DATA'!$D$2:$D$271) -> BATTERY | H301: =_xlfn.XLOOKUP(E301,'KING TON SALES__ RAW DATA'!$A$2:$A$271,'KING TON SALES__ RAW DATA'!$G$2:$G$271) -> 12000 | I301: 21 | J301: =_xlfn.XLOOKUP(E301,'KING TON SALES__ RAW DATA'!$A$2:$A$271,'KING TON SALES__ RAW DATA'!$I$2:$I$271) -> 18000 | K301: =H301*I301 -> 252000 | L301: =J301*I301 -> 378000 | M301: =L301-K301 -> 126000 | N301: =_xlfn.XLOOKUP(E301,'KING TON SALES__ RAW DATA'!$A$2:$A$271,'KING TON SALES__ RAW DATA'!$M$2:$M$271) -> POS

Sheet PIVOT TABLE
A1: CATEGORY | B1: Sum of REVENUE | C1: Sum of TOTAL PROFIT | E1: CITY | F1: Sum of REVENUE | G1: Sum of TOTAL PROFIT | I1: PRODUCT NAME | J1: Sum of QUANTITY SOLD
A2: BATTERY | B2: 3473500 | C2: 1134800 | E2: SAPELE | F2: 10338500 | G2: 5016500 | I2: 4K HDMI (50m) WIRE | J2: 129
A3: BLENDER | B3: 31500 | C3: 10500 | E3: WARRI | F3: 30983000 | G3: 12689700 | I3: 3 TO 3 AV (5m) WIRE | J3: 130
A4: ELECTRICAL | B4: 7783500 | C4: 3790700 | E4: AGBARO | F4: 4699500 | G4: 2330800 | I4: BENJOR MULTI WITH SWITCH | J4: 132
A5: SURGE | B5: 1736000 | C5: 1095000 | E5: UGHELLI | F5: 26305500 | G5: 9537900 | I5: HDMI (10m) WIRE | J5: 137
A6: TOOL | B6: 131500 | C6: 66600 | E6: OGHULA | F6: 4446500 | G6: 2192000 | I6: BLUE 4K HDMI (10m) WIRE | J6: 145
A7: WIRE | B7: 63617000 | C7: 25669300 | E7: Grand Total | F7: 76773000 | G7: 31766900 | I7: 13 AMPS SINGLE SOCKET NEW | J7: 155
A8: Grand Total | B8: 76773000 | C8: 31766900 | I8: BLUE 4K HDMI (3m) WIRE | J8: 165
I9: 4K HDMI (100m) WIRE | J9: 173
A10: PRODUCT NAME | B10: Sum of REVENUE | C10: Sum of TOTAL PROFIT | E10: PAYMENT METHOD | F10: Sum of REVENUE | G10: Sum of TOTAL PROFIT | I10: 3 TO 3 AV (10m) WIRE | J10: 174
A11: HDMI (50m) WIRE | B11: 1740000 | C11: 435000 | E11: CASH | F11: 21079000 | G11: 8787650 | I11: MULTI (APC) EXTENTION 6 MOUTH | J11: 213
A12: BLUE 4K HDMI (10m) WIRE | B12: 1740000 | C12: 870000 | E12: POS | F12: 28640500 | G12: 12503100 | I12: Grand Total | J12: 1553
A13: 4K HDMI (10m) WIRE | B13: 1830000 | C13: 1220000 | E13: TRANSFER | F13: 27053500 | G13: 10476150
A14: CAT 4 WIRE | B14: 2340000 | C14: 936000 | E14: Grand Total | F14: 76773000 | G14: 31766900
A15: MULTI (APC) EXTENTION 6 MOUTH | B15: 2556000 | C15: 1065000
A16: SNAKE (Tiny) WIRE | B16: 3540000 | C16: 1180000
A17: KAPU WIRE | B17: 4200000 | C17: 1680000 | E17: CUSTOMER TYPE | F17: Count of QUANTITY SOLD | G17: Sum of REVENUE | H17: Sum of TOTAL PROFIT
A18: ORIGINAL SPEAKER WIRE | B18: 4800000 | C18: 1800000 | E18: NORMAL | F18: 184 | G18: 52661000 | H18: 21841350
A19: 4K HDMI (50m) WIRE | B19: 5805000 | C19: 1935000 | E19: MEMEBER | F19: 116 | G19: 24112000 | H19: 9925550
A20: CAT 6 WIRE | B20: 6710000 | C20: 1830000 | E20: Grand Total | F20: 300 | G20: 76773000 | H20: 31766900
A21: 4K HDMI (100m) WIRE | B21: 17300000 | C21: 6920000
A22: Grand Total | B22: 52561000 | C22: 19871000 | E22: DATE | F22: Sum of REVENUE | G22: Sum of TOTAL PROFIT
E23: May | F23: 4590000 | G23: 1947900
E24: Jun | F24: 4666500 | G24: 2367900
E25: Jul | F25: 31884500 | G25: 12495100
E26: Aug | F26: 35632000 | G26: 14956000
E27: Grand Total | F27: 76773000 | G27: 31766900

Sheet KPI
A2: Sum of TOTAL PROFIT | D2: Average of REVENUE
A3: 31766900 | D3: 255910
B7: Sum of REVENUE
B8: 76773000
E11: Count of QUANTITY SOLD
E12: 300
C13: Sum of QUANTITY SOLD
C14: 6270

Sheet DASHBOARD
